mcpengine/__init__.py
mcpengine/errors.py
mcpengine/py.typed
mcpengine/types.py
mcpengine/cli/__init__.py
mcpengine/cli/claude.py
mcpengine/cli/cli.py
mcpengine/cli/docker.py
mcpengine/client/__init__.py
mcpengine/client/__main__.py
mcpengine/client/session.py
mcpengine/client/sse.py
mcpengine/client/websocket.py
mcpengine/client/stdio/__init__.py
mcpengine/client/stdio/win32.py
mcpengine/client/transports/http.py
mcpengine/server/__init__.py
mcpengine/server/__main__.py
mcpengine/server/http.py
mcpengine/server/models.py
mcpengine/server/session.py
mcpengine/server/settings.py
mcpengine/server/sse.py
mcpengine/server/stdio.py
mcpengine/server/websocket.py
mcpengine/server/auth/__init__.py
mcpengine/server/auth/backend.py
mcpengine/server/auth/context.py
mcpengine/server/auth/errors.py
mcpengine/server/auth/providers/__init__.py
mcpengine/server/auth/providers/config.py
mcpengine/server/auth/providers/google.py
mcpengine/server/lowlevel/__init__.py
mcpengine/server/lowlevel/helper_types.py
mcpengine/server/lowlevel/server.py
mcpengine/server/mcpengine/__init__.py
mcpengine/server/mcpengine/exceptions.py
mcpengine/server/mcpengine/server.py
mcpengine/server/mcpengine/prompts/__init__.py
mcpengine/server/mcpengine/prompts/base.py
mcpengine/server/mcpengine/prompts/manager.py
mcpengine/server/mcpengine/prompts/prompt_manager.py
mcpengine/server/mcpengine/resources/__init__.py
mcpengine/server/mcpengine/resources/base.py
mcpengine/server/mcpengine/resources/resource_manager.py
mcpengine/server/mcpengine/resources/templates.py
mcpengine/server/mcpengine/resources/types.py
mcpengine/server/mcpengine/tools/__init__.py
mcpengine/server/mcpengine/tools/base.py
mcpengine/server/mcpengine/tools/tool_manager.py
mcpengine/server/mcpengine/utilities/__init__.py
mcpengine/server/mcpengine/utilities/func_metadata.py
mcpengine/server/mcpengine/utilities/logging.py
mcpengine/server/mcpengine/utilities/types.py
mcpengine/shared/__init__.py
mcpengine/shared/context.py
mcpengine-0.3.0.dist-info/licenses/LICENSE
mcpengine-0.3.0.dist-info/METADATA
mcpengine-0.3.0.dist-info/WHEEL
mcpengine-0.3.0.dist-info/entry_points.txt
mcpengine-0.3.0.dist-info/top_level.txt
mcpengine-0.3.0.dist-info/RECORD
