Metadata-Version: 2.4
Name: mcpengine
Version: 0.3.0
Summary: MCPEngine is a Model Context Protocol SDK built for Production
Author: Anthropic, PBC., Featureform, Inc.
Maintainer-email: Simba Khadder <simba@featureform.com>, Kamal Sadek <kamal@featureform.com>, Erik Eppel <erik@featureform.com>, Riddhi Bagadiaa <riddhi@featureform.com>
License: MIT
Project-URL: Homepage, https://www.featureform.com
Project-URL: Repository, https://github.com/featureform/mcp-engine
Project-URL: Issues, https://github.com/featureform/mcp-engine/issues
Keywords: git,mcp,mcpengine,llm,automation
Classifier: Development Status :: 4 - Beta
Classifier: Intended Audience :: Developers
Classifier: License :: OSI Approved :: MIT License
Classifier: Programming Language :: Python :: 3
Classifier: Programming Language :: Python :: 3.10
Classifier: Programming Language :: Python :: 3.11
Classifier: Programming Language :: Python :: 3.12
Classifier: Programming Language :: Python :: 3.13
Requires-Python: >=3.10
License-File: LICENSE
Requires-Dist: anyio>=4.5
Requires-Dist: httpx>=0.27
Requires-Dist: httpx-sse>=0.4
Requires-Dist: pydantic<3.0.0,>=2.7.2
Requires-Dist: starlette>=0.27
Requires-Dist: sse-starlette>=1.6.1
Requires-Dist: pydantic-settings>=2.5.2
Requires-Dist: uvicorn>=0.23.1
Requires-Dist: pyjwt[crypto]==2.10.1
Requires-Dist: async-lru==2.0.5
Provides-Extra: lambda
Requires-Dist: mangum==0.19.0; extra == "lambda"
Provides-Extra: rich
Requires-Dist: rich>=13.9.4; extra == "rich"
Provides-Extra: cli
Requires-Dist: typer>=0.12.4; extra == "cli"
Requires-Dist: python-dotenv>=1.0.0; extra == "cli"
Requires-Dist: docker>=7.1.0; extra == "cli"
Provides-Extra: ws
Requires-Dist: websockets>=15.0.1; extra == "ws"
Dynamic: license-file
